trinsic_api/__init__.py
trinsic_api/api_client.py
trinsic_api/api_response.py
trinsic_api/configuration.py
trinsic_api/exceptions.py
trinsic_api/py.typed
trinsic_api/rest.py
trinsic_api/api/__init__.py
trinsic_api/api/providers_api.py
trinsic_api/api/redirect_uris_api.py
trinsic_api/api/sessions_api.py
trinsic_api/api/verification_profiles_api.py
trinsic_api/models/__init__.py
trinsic_api/models/aadhaar_input.py
trinsic_api/models/add_redirect_uri_request.py
trinsic_api/models/add_redirect_uri_response.py
trinsic_api/models/address.py
trinsic_api/models/apple_wallet_input.py
trinsic_api/models/apple_wallet_provider_output.py
trinsic_api/models/attachment_info.py
trinsic_api/models/attribute_availability.py
trinsic_api/models/austria_handy_signatur_provider_output.py
trinsic_api/models/belgium_id_card_provider_output.py
trinsic_api/models/brazil_cpf_check_input.py
trinsic_api/models/brazil_digital_cnh_input.py
trinsic_api/models/cancel_session_response.py
trinsic_api/models/contract_attachment.py
trinsic_api/models/contract_attribute.py
trinsic_api/models/cote_d_ivoire_nid_lookup2_input.py
trinsic_api/models/create_direct_provider_session_request.py
trinsic_api/models/create_direct_provider_session_response.py
trinsic_api/models/create_hosted_provider_session_request.py
trinsic_api/models/create_hosted_provider_session_response.py
trinsic_api/models/create_verification_profile_response.py
trinsic_api/models/create_widget_session_request.py
trinsic_api/models/create_widget_session_response.py
trinsic_api/models/czechia_moje_id_provider_output.py
trinsic_api/models/document_data.py
trinsic_api/models/document_type.py
trinsic_api/models/estonia_id_card_provider_output.py
trinsic_api/models/fayda_provider_output.py
trinsic_api/models/finland_id_card_provider_output.py
trinsic_api/models/freja_provider_output.py
trinsic_api/models/french_numerique_given_name.py
trinsic_api/models/french_numerique_nationality.py
trinsic_api/models/french_numerique_phone.py
trinsic_api-3.0.0.dist-info/METADATA
trinsic_api-3.0.0.dist-info/WHEEL
trinsic_api-3.0.0.dist-info/top_level.txt
trinsic_api-3.0.0.dist-info/RECORD
