Metadata-Version: 2.1
Name: trinsic-api
Version: 3.0.0
Summary: Trinsic API
Home-page: https://trinsic.id
Author: trinsic-id
Author-email: support@trinsic.id
Keywords: Trinsic,SDK,Identity verification
Requires-Dist: pydantic >=2
Requires-Dist: python-dateutil >=2.8.2
Requires-Dist: typing-extensions >=4.7.1
Requires-Dist: urllib3 <3.0.0,>=2.1.0
